{"name":"Delete user successfully.","id":"create-user;delete-user-successfully.","testSteps":[{"number":1,"description":"When I consume the service and send the user ID","duration":9417,"startTime":"2023-08-30T11:19:12.415031700-05:00[America/Bogota]","result":"SUCCESS","precondition":false,"level":0,"children":[{"number":2,"description":"User delete user task","duration":9397,"startTime":"2023-08-30T11:19:12.426037-05:00[America/Bogota]","result":"SUCCESS","precondition":false,"level":1,"children":[{"number":3,"description":"user executes a DELETE on the resource /users/11","duration":9356,"startTime":"2023-08-30T11:19:12.457043200-05:00[America/Bogota]","result":"SUCCESS","precondition":false,"level":2,"children":[{"number":4,"description":"DELETE https://fakestoreapi.com/users/11","duration":1,"startTime":"2023-08-30T11:19:21.812935500-05:00[America/Bogota]","result":"SUCCESS","restQuery":{"method":"DELETE","path":"https://fakestoreapi.com/users/11","content":"","contentType":"application/json","requestHeaders":"Accept\u003d*/*\r\n\t\t\t\tContent-Type\u003dapplication/json","requestCookies":"","responseHeaders":"Date: Wed, 30 Aug 2023 16:19:21 GMT\r\nContent-Type: application/json; charset\u003dutf-8\r\nContent-Length: 4\r\nConnection: keep-alive\r\nAccess-Control-Allow-Origin: *\r\nEtag: W/\"4-K+iMpCQsduglOsYkdIUQZQMtaDM\"\r\nX-Powered-By: Express\r\nCF-Cache-Status: DYNAMIC\r\nReport-To: {\"endpoints\":[{\"url\":\"https:\\/\\/a.nel.cloudflare.com\\/report\\/v3?s\u003dwA925cueGjM88fnVZ1Y8OIuXWKnahrWapxHbf85LzGtmf%2FrHyvzsVsP5Fs9KL%2BSLIziAdKIdqlogZnLc6FHkIb6KLntND8AJeZhi0ENSm2XqXGSu7hLJ%2FSbRcItv8w%2BGv21r\"}],\"group\":\"cf-nel\",\"max_age\":604800}\r\nNEL: {\"success_fraction\":0,\"report_to\":\"cf-nel\",\"max_age\":604800}\r\nServer: cloudflare\r\nCF-RAY: 7fee5aa44e77da8f-MIA\r\nalt-svc: h3\u003d\":443\"; ma\u003d86400\r","responseCookies":"\r","responseBody":"null","statusCode":200},"precondition":false,"level":3}]}]}]},{"number":5,"description":"Then I can validate the data in the service response","duration":76,"startTime":"2023-08-30T11:19:21.833940500-05:00[America/Bogota]","exception":{"errorType":"java.lang.AssertionError","message":"null","stackTrace":[{"declaringClass":"com.fakestoreapi.stepDefinitions.DeleteUserStepDef","methodName":"iCanValidateTheDataInTheServiceResponse","fileName":"DeleteUserStepDef.java","lineNumber":45},{"declaringClass":"✽","methodName":"I can validate the data in the service response","fileName":"file:///C:/Users/Kevin/IdeaProjects/fakeStoreService/src/test/resources/features/FakeStoreApi.feature","lineNumber":16}]},"result":"FAILURE","precondition":false,"level":0,"children":[{"number":6,"description":"Then The response is not null: should be not null","duration":7,"startTime":"2023-08-30T11:19:21.840942200-05:00[America/Bogota]","result":"SUCCESS","precondition":false,"level":1},{"number":7,"description":"Then The phone response was should be \u00271-570-236-7033\u0027","duration":28,"startTime":"2023-08-30T11:19:21.851944200-05:00[America/Bogota]","exception":{"errorType":"java.lang.NullPointerException","stackTrace":[{"declaringClass":"com.fakestoreapi.stepDefinitions.DeleteUserStepDef","methodName":"lambda$iCanValidateTheDataInTheServiceResponse$1","fileName":"DeleteUserStepDef.java","lineNumber":52},{"declaringClass":"com.fakestoreapi.stepDefinitions.DeleteUserStepDef","methodName":"iCanValidateTheDataInTheServiceResponse","fileName":"DeleteUserStepDef.java","lineNumber":45},{"declaringClass":"io.cucumber.java.Invoker","methodName":"doInvoke","fileName":"Invoker.java","lineNumber":66},{"declaringClass":"io.cucumber.java.Invoker","methodName":"invoke","fileName":"Invoker.java","lineNumber":24},{"declaringClass":"io.cucumber.java.AbstractGlueDefinition","methodName":"invokeMethod","fileName":"AbstractGlueDefinition.java","lineNumber":47},{"declaringClass":"io.cucumber.java.JavaStepDefinition","methodName":"execute","fileName":"JavaStepDefinition.java","lineNumber":29},{"declaringClass":"io.cucumber.core.runner.CoreStepDefinition","methodName":"execute","fileName":"CoreStepDefinition.java","lineNumber":66},{"declaringClass":"io.cucumber.core.runner.PickleStepDefinitionMatch","methodName":"runStep","fileName":"PickleStepDefinitionMatch.java","lineNumber":63},{"declaringClass":"io.cucumber.core.runner.TestStep","methodName":"executeStep","fileName":"TestStep.java","lineNumber":85},{"declaringClass":"io.cucumber.core.runner.TestStep","methodName":"run","fileName":"TestStep.java","lineNumber":57},{"declaringClass":"io.cucumber.core.runner.PickleStepTestStep","methodName":"run","fileName":"PickleStepTestStep.java","lineNumber":51},{"declaringClass":"io.cucumber.core.runner.TestCase","methodName":"run","fileName":"TestCase.java","lineNumber":84},{"declaringClass":"io.cucumber.core.runner.Runner","methodName":"runPickle","fileName":"Runner.java","lineNumber":75},{"declaringClass":"io.cucumber.core.runtime.CucumberExecutionContext","methodName":"lambda$runTestCase$5","fileName":"CucumberExecutionContext.java","lineNumber":129},{"declaringClass":"io.cucumber.core.runtime.RethrowingThrowableCollector","methodName":"executeAndThrow","fileName":"RethrowingThrowableCollector.java","lineNumber":23},{"declaringClass":"io.cucumber.core.runtime.CucumberExecutionContext","methodName":"runTestCase","fileName":"CucumberExecutionContext.java","lineNumber":129},{"declaringClass":"io.cucumber.junit.FeatureRunner","methodName":"runChild","fileName":"FeatureRunner.java","lineNumber":144},{"declaringClass":"io.cucumber.junit.FeatureRunner","methodName":"runChild","fileName":"FeatureRunner.java","lineNumber":28},{"declaringClass":"io.cucumber.junit.FeatureRunner","methodName":"run","fileName":"FeatureRunner.java","lineNumber":137},{"declaringClass":"io.cucumber.junit.CucumberSerenityRunner","methodName":"runChild","fileName":"CucumberSerenityRunner.java","lineNumber":259},{"declaringClass":"io.cucumber.junit.CucumberSerenityRunner","methodName":"runChild","fileName":"CucumberSerenityRunner.java","lineNumber":59},{"declaringClass":"worker.org.gradle.process.internal.worker.GradleWorkerMain","methodName":"run","fileName":"GradleWorkerMain.java","lineNumber":69},{"declaringClass":"worker.org.gradle.process.internal.worker.GradleWorkerMain","methodName":"main","fileName":"GradleWorkerMain.java","lineNumber":74}]},"result":"ERROR","precondition":false,"level":1}]}],"userStory":{"id":"create-user","storyName":"Create user","displayName":"Create user","path":"FakeStoreApi.feature","type":"feature","qualifiedTag":{"name":"Create user","type":"feature","displayName":"Create user"}},"featureTag":{"name":"Create user","type":"feature","displayName":"Create user"},"title":"Delete user successfully.","description":"","tags":[{"name":"Create user","type":"feature","displayName":"Create user"},{"name":"DeleteUser","type":"tag","displayName":"DeleteUser"}],"allTags":[{"name":"Create user","type":"feature","displayName":"Create user"},{"name":"DeleteUser","type":"tag","displayName":"DeleteUser"}],"startTime":"2023-08-30T11:19:12.370020500-05:00[America/Bogota]","duration":9545,"testFailureCause":{"errorType":"java.lang.NullPointerException","stackTrace":[{"declaringClass":"com.fakestoreapi.stepDefinitions.DeleteUserStepDef","methodName":"lambda$iCanValidateTheDataInTheServiceResponse$1","fileName":"DeleteUserStepDef.java","lineNumber":52},{"declaringClass":"com.fakestoreapi.stepDefinitions.DeleteUserStepDef","methodName":"iCanValidateTheDataInTheServiceResponse","fileName":"DeleteUserStepDef.java","lineNumber":45},{"declaringClass":"io.cucumber.java.Invoker","methodName":"doInvoke","fileName":"Invoker.java","lineNumber":66},{"declaringClass":"io.cucumber.java.Invoker","methodName":"invoke","fileName":"Invoker.java","lineNumber":24},{"declaringClass":"io.cucumber.java.AbstractGlueDefinition","methodName":"invokeMethod","fileName":"AbstractGlueDefinition.java","lineNumber":47},{"declaringClass":"io.cucumber.java.JavaStepDefinition","methodName":"execute","fileName":"JavaStepDefinition.java","lineNumber":29},{"declaringClass":"io.cucumber.core.runner.CoreStepDefinition","methodName":"execute","fileName":"CoreStepDefinition.java","lineNumber":66},{"declaringClass":"io.cucumber.core.runner.PickleStepDefinitionMatch","methodName":"runStep","fileName":"PickleStepDefinitionMatch.java","lineNumber":63},{"declaringClass":"io.cucumber.core.runner.TestStep","methodName":"executeStep","fileName":"TestStep.java","lineNumber":85},{"declaringClass":"io.cucumber.core.runner.TestStep","methodName":"run","fileName":"TestStep.java","lineNumber":57},{"declaringClass":"io.cucumber.core.runner.PickleStepTestStep","methodName":"run","fileName":"PickleStepTestStep.java","lineNumber":51},{"declaringClass":"io.cucumber.core.runner.TestCase","methodName":"run","fileName":"TestCase.java","lineNumber":84},{"declaringClass":"io.cucumber.core.runner.Runner","methodName":"runPickle","fileName":"Runner.java","lineNumber":75},{"declaringClass":"io.cucumber.core.runtime.CucumberExecutionContext","methodName":"lambda$runTestCase$5","fileName":"CucumberExecutionContext.java","lineNumber":129},{"declaringClass":"io.cucumber.core.runtime.RethrowingThrowableCollector","methodName":"executeAndThrow","fileName":"RethrowingThrowableCollector.java","lineNumber":23},{"declaringClass":"io.cucumber.core.runtime.CucumberExecutionContext","methodName":"runTestCase","fileName":"CucumberExecutionContext.java","lineNumber":129},{"declaringClass":"io.cucumber.junit.FeatureRunner","methodName":"runChild","fileName":"FeatureRunner.java","lineNumber":144},{"declaringClass":"io.cucumber.junit.FeatureRunner","methodName":"runChild","fileName":"FeatureRunner.java","lineNumber":28},{"declaringClass":"io.cucumber.junit.FeatureRunner","methodName":"run","fileName":"FeatureRunner.java","lineNumber":137},{"declaringClass":"io.cucumber.junit.CucumberSerenityRunner","methodName":"runChild","fileName":"CucumberSerenityRunner.java","lineNumber":259},{"declaringClass":"io.cucumber.junit.CucumberSerenityRunner","methodName":"runChild","fileName":"CucumberSerenityRunner.java","lineNumber":59},{"declaringClass":"worker.org.gradle.process.internal.worker.GradleWorkerMain","methodName":"run","fileName":"GradleWorkerMain.java","lineNumber":69},{"declaringClass":"worker.org.gradle.process.internal.worker.GradleWorkerMain","methodName":"main","fileName":"GradleWorkerMain.java","lineNumber":74}]},"testFailureClassname":"java.lang.NullPointerException","testFailureSummary":"ERROR;java.lang.NullPointerException;null;DeleteUserStepDef.java","projectKey":"","annotatedResult":"ERROR","isManualTestingUpToDate":false,"context":"windows","manual":false,"testSource":"Cucumber","actors":[{"name":"user","can":["call an API at https://fakestoreapi.com"]}],"result":"ERROR"}